{"_currentVersionState": {"$invariant": "DRAFT"}, "name": {"$invariant": "Need Some Help CTAs"}, "_updateDate": {"$invariant": "2023-06-27T03:59:39.11Z"}, "_hasChildren": false, "_level": 5, "_createDate": "2023-04-28T01:09:54.093Z", "_id": "ab4a0225-0105-43e6-8d97-678831e6636d", "_links": {"self": {"href": "https://api.umbraco.io/content/ab4a0225-0105-43e6-8d97-678831e6636d"}, "root": {"href": "https://api.umbraco.io/content"}, "children": {"href": "https://api.umbraco.io/content/ab4a0225-0105-43e6-8d97-678831e6636d/children"}, "publish": {"href": "https://api.umbraco.io/content/ab4a0225-0105-43e6-8d97-678831e6636d/publish"}, "unpublish": {"href": "https://api.umbraco.io/content/ab4a0225-0105-43e6-8d97-678831e6636d/unpublish"}, "contenttype": {"href": "https://api.umbraco.io/content/type/cTAList"}}, "contentTypeAlias": "cTAList", "parentId": "287174db-601b-438b-8881-5e3955d83bb5", "sortOrder": 3, "selectableVariant": {"$invariant": []}, "order": {"$invariant": []}, "align": {"$invariant": []}, "heading": {"$invariant": ""}, "text": {"$invariant": null}, "datasource": {"$invariant": "umb://document/342f652d216c40cf81d7debd004ee7e7"}, "backgroundColour": {"$invariant": ""}, "callToActionItems": {"$invariant": ""}}