{"_currentVersionState": {"$invariant": "PUBLISHED"}, "name": {"$invariant": "Why automate - 3 Column"}, "_updateDate": {"$invariant": "2023-12-18T10:27:20.437Z"}, "_hasChildren": false, "_level": 5, "_createDate": "2023-12-18T09:09:46.59Z", "_id": "6703b6da-8914-4097-be2a-4655b2f01cc2", "_links": {"self": {"href": "https://api.umbraco.io/content/6703b6da-8914-4097-be2a-4655b2f01cc2"}, "root": {"href": "https://api.umbraco.io/content"}, "children": {"href": "https://api.umbraco.io/content/6703b6da-8914-4097-be2a-4655b2f01cc2/children"}, "publish": {"href": "https://api.umbraco.io/content/6703b6da-8914-4097-be2a-4655b2f01cc2/publish"}, "unpublish": {"href": "https://api.umbraco.io/content/6703b6da-8914-4097-be2a-4655b2f01cc2/unpublish"}, "contenttype": {"href": "https://api.umbraco.io/content/type/keyFeatures"}}, "contentTypeAlias": "keyFeatures", "parentId": "c1a80d5d-c9cc-42fd-a88f-a6b6b65b33c7", "sortOrder": 3, "heading": {"$invariant": "Why automate with Automatic Technology?"}, "text": {"$invariant": "<p style=\"text-align: center;\">Automating your roller door makes entering and exiting your home a breeze. However, there are plenty of benefits beyond convenience. Automating your roller door on your home garage or shed can also make it safer and more secure.\u00a0</p>\n<p style=\"text-align: center;\"><br /><strong>Automatic Technology roller door openers:</strong></p>"}, "backgroundColour": {"$invariant": {"value": "f6f6f6", "label": "f6f6f6", "sortOrder": 1, "id": "6"}}, "selectableVariant": {"$invariant": ["Key Features - Three Column"]}, "order": {"$invariant": []}, "align": {"$invariant": []}, "maxItemsPerRow": {"$invariant": ""}, "colReverse": {"$invariant": ""}, "topRounded": {"$invariant": ""}, "bottomRounded": {"$invariant": ""}, "keyFeatures": {"$invariant": {"layout": {"Umbraco.BlockList": [{"contentUdi": "umb://element/986e1c4eea9641e496171c9e7f3e4369"}, {"contentUdi": "umb://element/258d052ea8014e6183f0f592eafd5b71"}, {"contentUdi": "umb://element/e411c51fe539477fb4288692a035497e"}, {"contentUdi": "umb://element/d145e6b4c4fe4f40be215b637358a0fe"}, {"contentUdi": "umb://element/5b776cd6f473439093da031be38f4e1b"}, {"contentUdi": "umb://element/4c4adda6ebd64b3aa6cc05b9207cf6d1"}]}, "contentData": [{"contentTypeKey": "17196671-6546-49fe-8882-35200721e887", "udi": "umb://element/986e1c4eea9641e496171c9e7f3e4369", "heading": "Help protect your family", "image": [{"key": "42ab1baa-6fd6-4078-a2dd-7216bba58087", "mediaKey": "e81e177f-e9be-4750-bc8a-8510f0ea0fa8", "crops": [], "focalPoint": null}], "description": "<p style=\"text-align: center;\">Automatic Technology roller door openers allow you to keep safe when entering and exiting your home late at night or in the middle of a storm.</p>"}, {"contentTypeKey": "17196671-6546-49fe-8882-35200721e887", "udi": "umb://element/258d052ea8014e6183f0f592eafd5b71", "heading": "Are easy to install", "image": [{"key": "ae4832d0-40f4-4179-9a91-73f09e190251", "mediaKey": "12ec4bf3-ff3f-4d51-af65-b6c0accb81ba", "crops": [], "focalPoint": null}], "description": "<p style=\"text-align: center;\">Automation installation made simple and reliable. You can count on Automatic Technology openers to lift and lower your garage door day in and day out for many years to come.</p>"}, {"contentTypeKey": "17196671-6546-49fe-8882-35200721e887", "udi": "umb://element/e411c51fe539477fb4288692a035497e", "heading": "Prevent unwanted entry", "image": [{"key": "7f4f2040-67ad-4ff1-9404-4d2bb531e008", "mediaKey": "50f68412-4e83-4fde-afe9-27c10c334707", "crops": [], "focalPoint": null}], "description": "<p style=\"text-align: center;\">Automatic back drive forces the door back down if it senses an intruder is trying to lift the door.</p>"}, {"contentTypeKey": "17196671-6546-49fe-8882-35200721e887", "udi": "umb://element/d145e6b4c4fe4f40be215b637358a0fe", "heading": "Feature In-built automatic reversing smarts", "image": [{"key": "f70454ae-2ee3-469f-a7ba-400e7bac4c2e", "mediaKey": "12ec4bf3-ff3f-4d51-af65-b6c0accb81ba", "crops": [], "focalPoint": null}], "description": "<p style=\"text-align: center;\">Reverses the door if it senses an obstruction is in the way.</p>"}, {"contentTypeKey": "17196671-6546-49fe-8882-35200721e887", "udi": "umb://element/5b776cd6f473439093da031be38f4e1b", "heading": "Provide in-built safety reminders", "image": [{"key": "12f820f4-67a0-47d3-b49a-cafc5bc501c2", "mediaKey": "e81e177f-e9be-4750-bc8a-8510f0ea0fa8", "crops": [], "focalPoint": null}], "description": "<p style=\"text-align: center;\">Just like your car, your garage door motor is full of moving parts that require periodic servicing to maintain its performance. ATA openers give you an audio and visual reminder when they\u2019re ready for a service</p>"}, {"contentTypeKey": "17196671-6546-49fe-8882-35200721e887", "udi": "umb://element/4c4adda6ebd64b3aa6cc05b9207cf6d1", "heading": "Are stress tested for durability", "image": [{"key": "224351e7-df0e-4dde-9a03-ee1fa7d1d690", "mediaKey": "8ce9fbcf-3524-4d1d-bc77-38a9274acb08", "crops": [], "focalPoint": null}], "description": "<p style=\"text-align: center;\">Soft start and stop technology reduces stress on the opener, which allows the door to open and close both quickly and quietly year after year, not just when it\u2019s installed.</p>"}], "settingsData": []}}}