{"_currentVersionState": {"$invariant": "PUBLISHED"}, "name": {"$invariant": "Page Rename Redirects"}, "_updateDate": {"$invariant": "2023-12-19T06:56:12.98Z"}, "_hasChildren": false, "_level": 5, "_createDate": "2023-12-19T02:11:03.457Z", "_id": "7e144e06-27a2-41b2-9057-a39f6d26291a", "_links": {"self": {"href": "https://api.umbraco.io/content/7e144e06-27a2-41b2-9057-a39f6d26291a"}, "root": {"href": "https://api.umbraco.io/content"}, "children": {"href": "https://api.umbraco.io/content/7e144e06-27a2-41b2-9057-a39f6d26291a/children"}, "publish": {"href": "https://api.umbraco.io/content/7e144e06-27a2-41b2-9057-a39f6d26291a/publish"}, "unpublish": {"href": "https://api.umbraco.io/content/7e144e06-27a2-41b2-9057-a39f6d26291a/unpublish"}, "contenttype": {"href": "https://api.umbraco.io/content/type/richtext"}}, "contentTypeAlias": "richtext", "parentId": "ebb5eb5b-6d98-458d-a7f6-91d1e6874667", "sortOrder": 1, "selectableVariant": {"$invariant": []}, "order": {"$invariant": []}, "align": {"$invariant": []}, "maxItemsPerRow": {"$invariant": ""}, "colReverse": {"$invariant": ""}, "topRounded": {"$invariant": ""}, "bottomRounded": {"$invariant": ""}, "backgroundColour": {"$invariant": ""}, "body": {"$invariant": "<h5>This page showcases the page rename redirect functionality</h5>\n<p>When a page is renamed, a redirect is created for the old url to the new one like so:</p>\n<p><img src=\"https://media.umbraco.io/norg-website/rd5l3wfc/rename-page.png?width=500&amp;height=364.3250688705234\" alt=\"rename page\" width=\"500\" height=\"364.3250688705234\" data-udi=\"umb://media/d8aeff8e4da24f5fbdb6addf19be8a78\" /></p>\n<p>so going to the old url should redirect the user to the new page.\u00a0 This section showcases that functionality.</p>"}}