{"_currentVersionState": {"$invariant": "PUBLISHED"}, "name": {"$invariant": "Securacode Remote"}, "_updateDate": {"$invariant": "2023-08-18T00:28:35.683Z"}, "_hasChildren": true, "_level": 4, "_createDate": "2023-05-23T06:03:45.77Z", "_id": "cc636e88-c304-4a1a-8954-167d42840161", "_links": {"self": {"href": "https://api.umbraco.io/content/cc636e88-c304-4a1a-8954-167d42840161"}, "root": {"href": "https://api.umbraco.io/content"}, "children": {"href": "https://api.umbraco.io/content/cc636e88-c304-4a1a-8954-167d42840161/children"}, "publish": {"href": "https://api.umbraco.io/content/cc636e88-c304-4a1a-8954-167d42840161/publish"}, "unpublish": {"href": "https://api.umbraco.io/content/cc636e88-c304-4a1a-8954-167d42840161/unpublish"}, "contenttype": {"href": "https://api.umbraco.io/content/type/productPage"}}, "contentTypeAlias": "productPage", "parentId": "20c706cb-91db-4119-81c2-dd8edbfc3827", "sortOrder": 2, "showInNavigation": {"$invariant": "1"}, "externalLink": {"$invariant": []}, "umbracoUrlName": {"$invariant": ""}, "superAlias": {"$invariant": ""}, "prefetch": {"$invariant": "1"}, "source": {"$invariant": ""}, "destination": {"$invariant": ""}, "isPermanent": {"$invariant": "1"}, "sEOTitle": {"$invariant": ""}, "sEODescription": {"$invariant": "Experience unparalleled protection with Hero SecuraCode, the advanced code hopping technology for garage doors. Offering over 4.29 billion random codes to prevent unauthorised access."}, "showInSitemap": {"$invariant": "1"}, "ogImage": {"$invariant": []}, "ogDescription": {"$invariant": "Experience unparalleled protection with Hero SecuraCode, the advanced code hopping technology for garage doors. Offering over 4.29 billion random codes to prevent unauthorised access."}, "canonicalURLContentItem": {"$invariant": ""}, "canonicalURLAbsolute": {"$invariant": ""}, "structuredData": {"$invariant": ""}, "noIndexPage": {"$invariant": "0"}, "alternateMultiURLs": {"$invariant": []}, "heading": {"$invariant": "Securacode Remote"}, "images": {"$invariant": []}, "productPhoto": {"$invariant": [{"key": "a8ea5ef4-62f0-4f32-b94d-14f1a4141600", "mediaKey": "2c22c5a2-5242-45fc-926a-98cb1ec26122", "crops": [], "focalPoint": null}]}, "productDescription": {"$invariant": "<p>Advanced code hopping technology remote.\u00a0</p>"}, "productFeature": {"$invariant": null}, "downloads": {"$invariant": {"layout": {"Umbraco.BlockList": [{"contentUdi": "umb://element/f063e191610c4d0b964a53955742cefa"}, {"contentUdi": "umb://element/61b2070f4de2403e8aa0c61f46cf565e"}]}, "contentData": [{"contentTypeKey": "dee3aa7c-ac98-4823-9669-df4f2838a5b6", "udi": "umb://element/f063e191610c4d0b964a53955742cefa", "heading": "Brochure", "image": [{"key": "8676b9f3-8dd6-4e1f-b5b6-e87e8aed8d7f", "mediaKey": "c9087300-9a59-412e-8f27-1f7ca5123e51", "crops": [], "focalPoint": null}], "media": [], "buttonText": "Download"}, {"contentTypeKey": "dee3aa7c-ac98-4823-9669-df4f2838a5b6", "udi": "umb://element/61b2070f4de2403e8aa0c61f46cf565e", "heading": "User Manual", "image": [{"key": "d69eed96-33c0-48b6-8abd-dcd7d523463a", "mediaKey": "6e00be17-e48a-48ae-92d1-551f96ae0dc5", "crops": [], "focalPoint": null}], "media": [{"key": "c91fd9ae-d37c-4e6a-af07-887c7d3761c3", "mediaKey": "3f8f62d9-f0d6-434c-ac0e-0050e47781ff", "crops": [], "focalPoint": null}], "buttonText": "Download"}], "settingsData": []}}, "productVideos": {"$invariant": []}, "productName": {"$invariant": ""}, "productGallery": {"$invariant": []}, "showStandardProductBody": {"$invariant": "1"}, "specifications": {"$invariant": ""}, "imageSectionContent": {"$invariant": ""}, "warranty": {"$invariant": null}, "features": {"$invariant": ""}, "frequentlyAskedQuestions": {"$invariant": null}, "rows": {"$invariant": ""}, "turnOnAdvancedProductSpecificationTable": {"$invariant": "0"}}