{"_currentVersionState": {"$invariant": "PUBLISHED"}, "name": {"$invariant": "PRODUCT BROCHURES"}, "_updateDate": {"$invariant": "2023-07-04T09:37:24.08Z"}, "_hasChildren": true, "_level": 5, "_createDate": "2023-07-04T09:35:56.373Z", "_id": "b3898de5-9e3e-486f-8455-6f13a1eddfa7", "_links": {"self": {"href": "https://api.umbraco.io/content/b3898de5-9e3e-486f-8455-6f13a1eddfa7"}, "root": {"href": "https://api.umbraco.io/content"}, "children": {"href": "https://api.umbraco.io/content/b3898de5-9e3e-486f-8455-6f13a1eddfa7/children"}, "publish": {"href": "https://api.umbraco.io/content/b3898de5-9e3e-486f-8455-6f13a1eddfa7/publish"}, "unpublish": {"href": "https://api.umbraco.io/content/b3898de5-9e3e-486f-8455-6f13a1eddfa7/unpublish"}, "contenttype": {"href": "https://api.umbraco.io/content/type/accordion"}}, "contentTypeAlias": "accordion", "parentId": "3c8a16a6-8516-493f-bd1d-6a257d8a2aa7", "sortOrder": 2, "backgroundColour": {"$invariant": ""}, "selectableVariant": {"$invariant": []}, "order": {"$invariant": []}, "align": {"$invariant": []}}